AUTHORS.txt
LICENSE.txt
MANIFEST.in
NEWS.txt
README.rst
setup.py
src/django_sunset.egg-info/PKG-INFO
src/django_sunset.egg-info/SOURCES.txt
src/django_sunset.egg-info/dependency_links.txt
src/django_sunset.egg-info/not-zip-safe
src/django_sunset.egg-info/top_level.txt
src/sunset/__init__.py
src/sunset/api.py
src/sunset/collection.py
src/sunset/roles.py
src/sunset/tests/__init__.py
src/sunset/tests/test_api.py
src/sunset/tests/working/__init__.py