Metadata-Version: 1.0
Name: django-sunset
Version: 0.3
Summary: Handle Django settings in a bit more organized fashion
Home-page: http://github.com/robmadole/django-sunset
Author: Rob Madole
Author-email: robmadole@gmail.com
License: BSD
Keywords: django settings
Platform: UNKNOWN
Classifier: Development Status :: 4 - Beta
Classifier: Framework :: Django
Classifier: Intended Audience :: Developers
Classifier: Intended Audience :: System Administrators
Classifier: License :: OSI Approved :: BSD License
Classifier: Operating System :: OS Independent
